{
    "web": {
        "client_id": "591145464095-jlg6htno9ohmmpfbv75hgm9hsp9uekpu.apps.googleusercontent.com",
        "project_id": "linen-momentum-277711",
        "auth_uri": "https://accounts.google.com/o/oauth2/auth",
        "token_uri": "https://oauth2.googleapis.com/token",
        "auth_provider_x509_cert_url": "https://www.googleapis.com/oauth2/v1/certs",
        "client_secret": "GWJ0t0MYWRysxnU2YU-cpxlW",
        "javascript_origins": ["https://kzkmichal-slider.netlify.app", "http://localhost:8080"]
    }
}